{
  "type": "minecraft:crafting_shapeless",
  "ingredients": [
    {
      "item": "toomanyresources:raw_kirionite"
    },
    {
      "item": "toomanyresources:raw_kirionite"
    },
    {
      "item": "toomanyresources:raw_kirionite"
    },
    {
      "item": "toomanyresources:raw_kirionite"
    },
    {
      "item": "toomanyresources:raw_kirionite"
    },
    {
      "item": "toomanyresources:raw_kirionite"
    },
    {
      "item": "toomanyresources:raw_kirionite"
    },
    {
      "item": "toomanyresources:raw_kirionite"
    },
    {
      "item": "toomanyresources:raw_kirionite"
    }
  ],
  "result": {
    "item": "toomanyresources:raw_kirionite_block"
  }
}