{
  "parent": "minecraft:recipes/root",
  "rewards": {
    "recipes": [
      "toomanyresources:helminium_ingot_from_smelting_endstone_helminium_ore"
    ]
  },
  "criteria": {
    "has_endstone_helminium_ore": {
      "trigger": "minecraft:inventory_changed",
      "conditions": {
        "items": [
          {
            "items": [
              "toomanyresources:endstone_helminium_ore"
            ]
          }
        ]
      }
    },
    "has_the_recipe": {
      "trigger": "minecraft:recipe_unlocked",
      "conditions": {
        "recipe": "toomanyresources:helminium_ingot_from_smelting_endstone_helminium_ore"
      }
    }
  },
  "requirements": [
    [
      "has_endstone_helminium_ore",
      "has_the_recipe"
    ]
  ]
}